blond/__init__.py
blond/_version.py
blond/compile.py
blond/sanity_check.py
blond/beam/__init__.py
blond/beam/beam.py
blond/beam/coasting_beam.py
blond/beam/distributions.py
blond/beam/distributions_multibunch.py
blond/beam/profile.py
blond/beam/sparse_slices.py
blond/cpp_routines/blondmath.cpp
blond/cpp_routines/convolution.cpp
blond/cpp_routines/cos.h
blond/cpp_routines/drift.cpp
blond/cpp_routines/exp.h
blond/cpp_routines/fast_resonator.cpp
blond/cpp_routines/histogram.cpp
blond/cpp_routines/kick.cpp
blond/cpp_routines/libblond.so
blond/cpp_routines/linear_interp_kick.cpp
blond/cpp_routines/mean_std_whereint.cpp
blond/cpp_routines/music_track.cpp
blond/cpp_routines/sin.h
blond/cpp_routines/sincos.h
blond/cpp_routines/vdtcore_common.h
blond/impedances/__init__.py
blond/impedances/impedance.py
blond/impedances/impedance_sources.py
blond/impedances/induced_voltage_analytical.py
blond/impedances/music.py
blond/input_parameters/__init__.py
blond/input_parameters/rf_parameters.py
blond/input_parameters/rf_parameters_options.py
blond/input_parameters/ring.py
blond/input_parameters/ring_options.py
blond/llrf/__init__.py
blond/llrf/beam_feedback.py
blond/llrf/cavity_feedback.py
blond/llrf/impulse_response.py
blond/llrf/notch_filter.py
blond/llrf/rf_modulation.py
blond/llrf/rf_noise.py
blond/llrf/signal_processing.py
blond/monitors/__init__.py
blond/monitors/monitors.py
blond/plots/__init__.py
blond/plots/plot.py
blond/plots/plot_beams.py
blond/plots/plot_impedance.py
blond/plots/plot_llrf.py
blond/plots/plot_parameters.py
blond/plots/plot_slices.py
blond/synchrotron_radiation/__init__.py
blond/synchrotron_radiation/synchrotron_radiation.py
blond/toolbox/__init__.py
blond/toolbox/action.py
blond/toolbox/convolution.py
blond/toolbox/diffusion.py
blond/toolbox/filters_and_fitting.py
blond/toolbox/logger.py
blond/toolbox/next_regular.py
blond/toolbox/parameter_scaling.py
blond/toolbox/tomoscope.py
blond-2.0.0.dist-info/DESCRIPTION.rst
blond-2.0.0.dist-info/METADATA
blond-2.0.0.dist-info/RECORD
blond-2.0.0.dist-info/WHEEL
blond-2.0.0.dist-info/metadata.json
blond-2.0.0.dist-info/top_level.txt
