Metadata-Version: 2.0
Name: blond
Version: 2.0.0
Summary: CERN code for simulating longitudinal beam dynamics in synchrotrons.
Home-page: https://github.com/blond-admin/BLonD
Author: Helga Timko et al.
Author-email: helga.timko@cern.ch
Maintainer: Konstantinos Iliakis
Maintainer-email: konstantinos.iliakis@cern.ch
License: UNKNOWN
Download-URL: https://github.com/blond-admin/BLonD/archive/v2.0.0.tar.gz
Keywords: Beam Longitudinal Dynamics Synchrotrons CERN
Platform: UNKNOWN
Classifier: Programming Language :: Python :: 3
Classifier: License :: OSI Approved :: GNU General Public License v3 (GPLv3)
Classifier: Operating System :: OS Independent
